[
  {
    "sender": "stone_anay",
    "count": 1,
    "handled": true
  },
  {
    "sender": "anakrantau01369",
    "count": 1,
    "handled": true
  },
  {
    "sender": "cahyadigehenk82",
    "count": 1,
    "handled": true
  },
  {
    "sender": "anton.singal",
    "count": 1,
    "handled": true
  },
  {
    "sender": "taufik_luki10",
    "count": 1,
    "handled": true
  },
  {
    "sender": "ripkimaulana572",
    "count": 1,
    "handled": true
  },
  {
    "sender": "lytta_s",
    "count": 1,
    "handled": true
  },
  {
    "sender": "yuda.tobar",
    "count": 1,
    "handled": true
  },
  {
    "sender": "andiramdani40",
    "count": 1,
    "handled": true
  },
  {
    "sender": "anggahadid0",
    "count": 1,
    "handled": true
  },
  {
    "sender": "dadang.desgh",
    "count": 1,
    "handled": true
  }
]